odoo10_addon_sale_blanket_order-10.0.1.0.0.99.dev8-py3.6-nspkg.pth
odoo/addons/sale_blanket_order/README.rst
odoo/addons/sale_blanket_order/__init__.py
odoo/addons/sale_blanket_order/__manifest__.py
odoo/addons/sale_blanket_order/data/ir_cron.xml
odoo/addons/sale_blanket_order/data/sequence.xml
odoo/addons/sale_blanket_order/i18n/ca.po
odoo/addons/sale_blanket_order/i18n/sale_blanket_order.pot
odoo/addons/sale_blanket_order/models/__init__.py
odoo/addons/sale_blanket_order/models/blanket_orders.py
odoo/addons/sale_blanket_order/models/sale_config_settings.py
odoo/addons/sale_blanket_order/models/sale_orders.py
odoo/addons/sale_blanket_order/report/report.xml
odoo/addons/sale_blanket_order/report/templates.xml
odoo/addons/sale_blanket_order/security/ir.model.access.csv
odoo/addons/sale_blanket_order/security/security.xml
odoo/addons/sale_blanket_order/static/description/icon.png
odoo/addons/sale_blanket_order/tests/__init__.py
odoo/addons/sale_blanket_order/tests/test_blanket_orders.py
odoo/addons/sale_blanket_order/views/blanket_orders.xml
odoo/addons/sale_blanket_order/views/sale_config_settings.xml
odoo/addons/sale_blanket_order/views/sale_orders.xml
odoo/addons/sale_blanket_order/wizard/__init__.py
odoo/addons/sale_blanket_order/wizard/create_sale_orders.py
odoo/addons/sale_blanket_order/wizard/create_sale_orders.xml
odoo10_addon_sale_blanket_order-10.0.1.0.0.99.dev8.dist-info/METADATA
odoo10_addon_sale_blanket_order-10.0.1.0.0.99.dev8.dist-info/WHEEL
odoo10_addon_sale_blanket_order-10.0.1.0.0.99.dev8.dist-info/namespace_packages.txt
odoo10_addon_sale_blanket_order-10.0.1.0.0.99.dev8.dist-info/top_level.txt
odoo10_addon_sale_blanket_order-10.0.1.0.0.99.dev8.dist-info/RECORD
